{
  "season": "2015-16",
  "tournament_id": 24,
  "conference_name": "OHIO VALLEY CONFERENCE WOMEN'S TOURNAMENT",
  "num_teams": 8,
  "regions": [],
  "games": [
    {
      "game_id": 400868360,
      "round": 1,
      "region": null,
      "home_team_id": 2630,
      "away_team_id": 93,
      "home_seed": null,
      "away_seed": null,
      "home_score": null,
      "away_score": null
    },
    {
      "game_id": 400868363,
      "round": 1,
      "region": null,
      "home_team_id": 2057,
      "away_team_id": 2634,
      "home_seed": null,
      "away_seed": null,
      "home_score": null,
      "away_score": null
    },
    {
      "game_id": 400868361,
      "round": 1,
      "region": null,
      "home_team_id": 2198,
      "away_team_id": 2046,
      "home_seed": null,
      "away_seed": null,
      "home_score": null,
      "away_score": null
    },
    {
      "game_id": 400868362,
      "round": 1,
      "region": null,
      "home_team_id": 2565,
      "away_team_id": 2546,
      "home_seed": null,
      "away_seed": null,
      "home_score": null,
      "away_score": null
    },
    {
      "game_id": 400869807,
      "round": 2,
      "region": null,
      "home_team_id": 2198,
      "away_team_id": 93,
      "home_seed": null,
      "away_seed": null,
      "home_score": null,
      "away_score": null
    },
    {
      "game_id": 400869877,
      "round": 2,
      "region": null,
      "home_team_id": 2057,
      "away_team_id": 2565,
      "home_seed": null,
      "away_seed": null,
      "home_score": null,
      "away_score": null
    },
    {
      "game_id": 400869971,
      "round": 3,
      "region": null,
      "home_team_id": 2057,
      "away_team_id": 2198,
      "home_seed": null,
      "away_seed": null,
      "home_score": null,
      "away_score": null
    }
  ]
}