{
  "season": "2021-22",
  "tournament_id": 19,
  "conference_name": "MVC Tournament",
  "num_teams": 10,
  "regions": [],
  "games": [
    {
      "game_id": 401402633,
      "round": 1,
      "region": null,
      "home_team_id": 282,
      "away_team_id": 339,
      "home_seed": null,
      "away_seed": null,
      "home_score": null,
      "away_score": null
    },
    {
      "game_id": 401402634,
      "round": 1,
      "region": null,
      "home_team_id": 2181,
      "away_team_id": 71,
      "home_seed": null,
      "away_seed": null,
      "home_score": null,
      "away_score": null
    },
    {
      "game_id": 401402635,
      "round": 2,
      "region": null,
      "home_team_id": 79,
      "away_team_id": 282,
      "home_seed": null,
      "away_seed": null,
      "home_score": null,
      "away_score": null
    },
    {
      "game_id": 401402636,
      "round": 2,
      "region": null,
      "home_team_id": 2287,
      "away_team_id": 2350,
      "home_seed": null,
      "away_seed": null,
      "home_score": null,
      "away_score": null
    },
    {
      "game_id": 401402637,
      "round": 2,
      "region": null,
      "home_team_id": 2623,
      "away_team_id": 2181,
      "home_seed": null,
      "away_seed": null,
      "home_score": null,
      "away_score": null
    },
    {
      "game_id": 401402638,
      "round": 2,
      "region": null,
      "home_team_id": 2460,
      "away_team_id": 2674,
      "home_seed": null,
      "away_seed": null,
      "home_score": null,
      "away_score": null
    },
    {
      "game_id": 401402639,
      "round": 3,
      "region": null,
      "home_team_id": 79,
      "away_team_id": 2287,
      "home_seed": null,
      "away_seed": null,
      "home_score": null,
      "away_score": null
    },
    {
      "game_id": 401402640,
      "round": 3,
      "region": null,
      "home_team_id": 2623,
      "away_team_id": 2460,
      "home_seed": null,
      "away_seed": null,
      "home_score": null,
      "away_score": null
    },
    {
      "game_id": 401402641,
      "round": 4,
      "region": null,
      "home_team_id": 2460,
      "away_team_id": 2287,
      "home_seed": null,
      "away_seed": null,
      "home_score": null,
      "away_score": null
    }
  ]
}